just_utils/__init__.py
just_utils/io.py
just_utils/meter.py
just_utils-0.1.3.dist-info/LICENSE
just_utils-0.1.3.dist-info/METADATA
just_utils-0.1.3.dist-info/WHEEL
just_utils-0.1.3.dist-info/top_level.txt
just_utils-0.1.3.dist-info/RECORD
