Metadata-Version: 2.1
Name: just-utils
Version: 0.1.3
Summary: A series of convenience functions to help training large image dataset with CNN
Home-page: https://github.com/Hansoluo/cvutils.git
Author: Hansoluo
Author-email: hansoluo757@gmail.com
License: UNKNOWN
Platform: UNKNOWN
Classifier: Programming Language :: Python :: 3
Classifier: License :: OSI Approved :: MIT License
Requires-Python: >=3.6
Requires-Dist: easydict
Requires-Dist: PyYAML
